H4sh/__init__.py
H4sh/fix.py
H4sh/secure_hash.py
H4sh/lib/gpu_hash.dll
H4sh/lib/secure_hash.dll
h4sh-0.9.1.dist-info/licenses/LICENSE
h4sh-0.9.1.dist-info/METADATA
h4sh-0.9.1.dist-info/WHEEL
h4sh-0.9.1.dist-info/top_level.txt
h4sh-0.9.1.dist-info/RECORD
