Metadata-Version: 2.4
Name: H4sh
Version: 0.9.1
Summary: A Python module for secure hashing using a C implementation
Author: pavlkon
License-Expression: MIT
Classifier: Programming Language :: Python :: 3
Classifier: Programming Language :: C
Classifier: Programming Language :: Python :: Implementation :: CPython
Classifier: Operating System :: Microsoft :: Windows
License-File: LICENSE
Dynamic: license-file
